LICENSE.md
README.rst
setup.cfg
setup.py
tornado_coroutines_opentracing/__init__.py
tornado_coroutines_opentracing.egg-info/PKG-INFO
tornado_coroutines_opentracing.egg-info/SOURCES.txt
tornado_coroutines_opentracing.egg-info/dependency_links.txt
tornado_coroutines_opentracing.egg-info/requires.txt
tornado_coroutines_opentracing.egg-info/top_level.txt