Metadata-Version: 1.2
Name: tornado-coroutines-opentracing
Version: 0.1.0
Summary: Opentracing instrumentation for Tornado that allows correct parent scope propagation for fire & forget coroutines.
Home-page: https://github.com/condorcet/tornado-coroutines-opentracing
Author: Vasilii Novikov
Author-email: novikov.vz@gmail.com
License: MIT
Keywords: opentracing,tornado
Platform: any
Classifier: Development Status :: 3 - Alpha
Classifier: Intended Audience :: Developers
Classifier: License :: OSI Approved :: MIT License
Classifier: Operating System :: OS Independent
Classifier: Programming Language :: Python
Classifier: Programming Language :: Python :: 2.7
Classifier: Programming Language :: Python :: 3.4
Classifier: Programming Language :: Python :: 3.5
Classifier: Programming Language :: Python :: 3.6
Classifier: Programming Language :: Python :: 3.7
Classifier: Topic :: Software Development :: Libraries :: Python Modules
Requires-Python: >=2.7
